{"totalCounts":{"Roy C.":52,"Estebi M.":158,"Agus V.":114,"Felipe Gonzalez":194,"Joaco L.":52,"Maxi":112,"Fran G.":145,"DanielMartinez~":71,"Nahuel G":68},"countsByMonth":{"2024-07":{"Roy C.":29,"Estebi M.":62,"Agus V.":41,"Felipe Gonzalez":74,"Joaco L.":45,"Maxi":36,"Fran G.":62,"DanielMartinez~":26},"2024-08":{"Felipe Gonzalez":75,"DanielMartinez~":29,"Estebi M.":63,"Roy C.":23,"Joaco L.":7,"Maxi":44,"Fran G.":52,"Agus V.":43,"Nahuel G":29},"2024-09":{"Agus V.":30,"DanielMartinez~":16,"Felipe Gonzalez":45,"Nahuel G":39,"Fran G.":31,"Maxi":32,"Estebi M.":33}},"lastUpdated":"2024-09-20T16:26:10.722Z"}
